project_conf/__init__.py
project_conf/core.py
project_conf-0.1.2.dist-info/METADATA
project_conf-0.1.2.dist-info/WHEEL
project_conf-0.1.2.dist-info/licenses/LICENSE
project_conf-0.1.2.dist-info/RECORD
