Metadata-Version: 2.4
Name: project-conf
Version: 0.1.2
Summary: Dictionary-style configuration with path helpers and automatic environment variable handling
Project-URL: Homepage, https://github.com/xychenmsn/project-conf
Project-URL: Documentation, https://github.com/xychenmsn/project-conf#readme
Project-URL: Repository, https://github.com/xychenmsn/project-conf
Project-URL: Issues, https://github.com/xychenmsn/project-conf/issues
Project-URL: Changelog, https://github.com/xychenmsn/project-conf/blob/main/CHANGELOG.md
Author-email: importal <xychen@msn.com>
Maintainer-email: importal <xychen@msn.com>
License: MIT License
License-File: LICENSE
Keywords: config,configuration,dictionary,environment,path-helpers,settings
Classifier: Development Status :: 4 - Beta
Classifier: Intended Audience :: Developers
Classifier: License :: OSI Approved :: MIT License
Classifier: Operating System :: OS Independent
Classifier: Programming Language :: Python :: 3
Classifier: Programming Language :: Python :: 3.8
Classifier: Programming Language :: Python :: 3.9
Classifier: Programming Language :: Python :: 3.10
Classifier: Programming Language :: Python :: 3.11
Classifier: Programming Language :: Python :: 3.12
Classifier: Topic :: Software Development :: Libraries :: Python Modules
Classifier: Topic :: System :: Systems Administration
Classifier: Topic :: Utilities
Requires-Python: >=3.8
Provides-Extra: dev
Requires-Dist: black>=23.0.0; extra == 'dev'
Requires-Dist: flake8>=6.0.0; extra == 'dev'
Requires-Dist: isort>=5.12.0; extra == 'dev'
Requires-Dist: mypy>=1.0.0; extra == 'dev'
Requires-Dist: pre-commit>=3.0.0; extra == 'dev'
Requires-Dist: pytest-cov>=4.0.0; extra == 'dev'
Requires-Dist: pytest>=7.0.0; extra == 'dev'
Provides-Extra: docs
Requires-Dist: mkdocs-material>=9.0.0; extra == 'docs'
Requires-Dist: mkdocs>=1.4.0; extra == 'docs'
Requires-Dist: mkdocstrings[python]>=0.20.0; extra == 'docs'
